pytest_databricks/__init__.py
pytest_databricks/client.py
pytest_databricks/helper.py
pytest_databricks/plugin.py
pytest_databricks/pytest_plugin.py
pytest_databricks/unittest.py
pytest_databricks/plugin/__init__.py
pytest_databricks/pytest/__init__.py
pytest_databricks/pytest/client.py
pytest_databricks/pytest/plugin.py
tests/__init__.py
tests/conftest.py
tests/test_basic.py
pytest_databricks-0.0.8.dist-info/LICENSE
pytest_databricks-0.0.8.dist-info/METADATA
pytest_databricks-0.0.8.dist-info/WHEEL
pytest_databricks-0.0.8.dist-info/entry_points.txt
pytest_databricks-0.0.8.dist-info/top_level.txt
pytest_databricks-0.0.8.dist-info/RECORD
