Metadata-Version: 2.1
Name: pytest-databricks
Version: 0.0.8
Summary: Pytest plugin for remote Databricks notebooks testing
Home-page: https://github.com/ivangeorgiev/pytest-databricks
Author: Ivan Georgiev
License: UNKNOWN
Platform: UNKNOWN
Classifier: Programming Language :: Python :: 3
Classifier: License :: OSI Approved :: MIT License
Classifier: Operating System :: OS Independent
Classifier: Framework :: Pytest
Requires-Python: >=3.6
Requires-Dist: pydbr
Requires-Dist: pytest
